dmoj_tool/__init__.py
dmoj_tool/cli.py
dmoj_tool/dmoj_tool.py
dmoj_tool/main.py
dmoj_tool_dessertion-0.1.7.dist-info/LICENSE
dmoj_tool_dessertion-0.1.7.dist-info/METADATA
dmoj_tool_dessertion-0.1.7.dist-info/WHEEL
dmoj_tool_dessertion-0.1.7.dist-info/entry_points.txt
dmoj_tool_dessertion-0.1.7.dist-info/top_level.txt
dmoj_tool_dessertion-0.1.7.dist-info/RECORD
