Metadata-Version: 2.1
Name: dmoj-tool-dessertion
Version: 0.1.7
Summary: CLI submission to DMOJ
Home-page: UNKNOWN
Author: Desertion
Author-email: 73731354pi@gmail.com
License: UNKNOWN
Platform: UNKNOWN
Requires-Python: >=3.6
Requires-Dist: beautifulsoup4
Requires-Dist: bs4
Requires-Dist: certifi
Requires-Dist: chardet
Requires-Dist: idna
Requires-Dist: requests
Requires-Dist: soupsieve
Requires-Dist: urllib3
